smark/__init__.py
smark/core.py
smark-1.0.0.dist-info/licenses/LICENSE
smark-1.0.0.dist-info/METADATA
smark-1.0.0.dist-info/WHEEL
smark-1.0.0.dist-info/top_level.txt
smark-1.0.0.dist-info/RECORD
