Metadata-Version: 2.4
Name: smark
Version: 1.0.0
Summary: SMARK logo
Author: SMARK
Author-email: SMARKpy@gmail.com
Requires-Python: >=3.7
License-File: LICENSE
Dynamic: author
Dynamic: author-email
Dynamic: license-file
Dynamic: requires-python
Dynamic: summary
